premsql/__init__.py
premsql/agents/__init__.py
premsql/agents/base.py
premsql/agents/baseline/__init__.py
premsql/agents/baseline/main.py
premsql/agents/baseline/prompts.py
premsql/agents/baseline/workers/__init__.py
premsql/agents/baseline/workers/analyser.py
premsql/agents/baseline/workers/followup.py
premsql/agents/baseline/workers/plotter.py
premsql/agents/baseline/workers/text2sql.py
premsql/agents/memory.py
premsql/agents/models.py
premsql/agents/router.py
premsql/agents/tools/__init__.py
premsql/agents/tools/plot/base.py
premsql/agents/tools/plot/matplotlib_tool.py
premsql/agents/utils.py
premsql/cli.py
premsql/datasets/__init__.py
premsql/datasets/base.py
premsql/datasets/collator.py
premsql/datasets/error_dataset.py
premsql/datasets/real/bird.py
premsql/datasets/real/domains.py
premsql/datasets/real/spider.py
premsql/datasets/synthetic/gretel.py
premsql/evaluator/README.md
premsql/evaluator/__init__.py
premsql/evaluator/base.py
premsql/executors/__init__.py
premsql/executors/base.py
premsql/executors/from_langchain.py
premsql/executors/from_sqlite.py
premsql/generators/__init__.py
premsql/generators/base.py
premsql/generators/huggingface.py
premsql/generators/mlx.py
premsql/generators/openai.py
premsql/generators/premai.py
premsql/logger.py
premsql/playground/__init__.py
premsql/playground/backend/api/__init__.py
premsql/playground/backend/api/admin.py
premsql/playground/backend/api/apps.py
premsql/playground/backend/api/migrations/0001_initial.py
premsql/playground/backend/api/migrations/__init__.py
premsql/playground/backend/api/models.py
premsql/playground/backend/api/pydantic_models.py
premsql/playground/backend/api/serializers.py
premsql/playground/backend/api/services.py
premsql/playground/backend/api/tests.py
premsql/playground/backend/api/urls.py
premsql/playground/backend/api/utils.py
premsql/playground/backend/api/views.py
premsql/playground/backend/backend/__init__.py
premsql/playground/backend/backend/asgi.py
premsql-0.2.4.dist-info/METADATA
premsql-0.2.4.dist-info/WHEEL
premsql-0.2.4.dist-info/entry_points.txt
premsql-0.2.4.dist-info/RECORD
