Metadata-Version: 2.1
Name: premsql
Version: 0.2.4
Summary: 
Author: Anindyadeep
Author-email: proanindyadeep@gmail.com
Requires-Python: >=3.10,<4.0
Classifier: Programming Language :: Python :: 3
Classifier: Programming Language :: Python :: 3.10
Classifier: Programming Language :: Python :: 3.11
Classifier: Programming Language :: Python :: 3.12
Provides-Extra: mac
Requires-Dist: SQLAlchemy (>=2.0.30,<3.0.0)
Requires-Dist: black (>=24.4.2,<25.0.0)
Requires-Dist: click (>=8.1.3,<9.0.0)
Requires-Dist: datasets (>=2.20.0,<3.0.0)
Requires-Dist: django (>=5.1.2,<6.0.0)
Requires-Dist: djangorestframework (>=3.15.2,<4.0.0)
Requires-Dist: drf-yasg (>=1.21.8,<2.0.0)
Requires-Dist: einops (>=0.8.0,<0.9.0)
Requires-Dist: fastapi (>=0.112.0,<0.113.0)
Requires-Dist: func_timeout (>=4.3.5,<5.0.0)
Requires-Dist: huggingface-hub (>=0.24.5,<0.25.0)
Requires-Dist: isort (>=5.13.2,<6.0.0)
Requires-Dist: kagglehub (>=0.3.3,<0.4.0)
Requires-Dist: langchain-community (>=0.3.3,<0.4.0)
Requires-Dist: matplotlib (>=3.9.2,<4.0.0)
Requires-Dist: mysql-connector-python (>=9.0.0,<10.0.0)
Requires-Dist: numpy (>=1.26.3,<2.0.0)
Requires-Dist: openai (>=1.52.0,<2.0.0)
Requires-Dist: pillow (>=8,<11)
Requires-Dist: premai (>=0.3.73,<0.4.0)
Requires-Dist: sqlparse (>=0.5.1,<0.6.0)
Requires-Dist: streamlit (>=1.32.0,<2.0.0)
Requires-Dist: tqdm (>=4.66.4,<5.0.0)
Requires-Dist: uvicorn (>=0.32.0,<0.33.0)
